scrape_deets/__init__.py
scrape_deets/github.py
scrape_deets-1.1.1.dist-info/LICENSE
scrape_deets-1.1.1.dist-info/METADATA
scrape_deets-1.1.1.dist-info/WHEEL
scrape_deets-1.1.1.dist-info/top_level.txt
scrape_deets-1.1.1.dist-info/RECORD
