Metadata-Version: 2.1
Name: scrape-deets
Version: 1.1.1
Summary: Populate data of an user by scrapping the data from various platforms like GitHub, Twitter, Instagram, etc
Author-email: Nikhil Raj <nikhil25803@gmail.com>
Classifier: Programming Language :: Python :: 3
Classifier: License :: OSI Approved :: MIT License
Classifier: Operating System :: OS Independent
Requires-Python: >=3.7
License-File: LICENSE
Requires-Dist: bs4 (>=0.0.1)
Requires-Dist: requests
